{
  "id": "yahoo-795d6631a12f7971",
  "source": "yahoo_finance",
  "type": "news",
  "title": "Apple iPhone 17 Anticipation Builds. Is Apple Stock A Buy?",
  "content": "",
  "url": "https://finance.yahoo.com/m/5c26a21e-1698-3c28-a2bb-c81df6d77d0f/apple-iphone-17-anticipation.html",
  "author": "Investor's Business Daily",
  "published_at": "2025-08-18T18:47:42+05:30",
  "ingested_at": "2025-08-18T21:59:31.4793713+05:30",
  "metadata": {
    "primary_symbol": "AAPL",
    "publisher": "Investor's Business Daily",
    "related_tickers": [
      "AAPL",
      "GOOG"
    ]
  },
  "tags": [
    "yahoo_finance",
    "financial_news",
    "AAPL"
  ],
  "entities": null
}
