{
  "id": "yahoo-1c70e7af929e3363",
  "source": "yahoo_finance",
  "type": "news",
  "title": "Do Stocks Have the Fuel To Move Higher?",
  "content": "",
  "url": "https://finance.yahoo.com/news/stocks-fuel-move-higher-211100585.html",
  "author": "Zacks",
  "published_at": "2025-08-15T02:41:00+05:30",
  "ingested_at": "2025-08-18T21:57:38.227347+05:30",
  "metadata": {
    "primary_symbol": "SPY",
    "publisher": "Zacks",
    "related_tickers": [
      "TPR",
      "SPY",
      "DE"
    ]
  },
  "tags": [
    "yahoo_finance",
    "financial_news",
    "SPY"
  ],
  "entities": null
}
