{
  "id": "marketwatch-a542998f339ebfb3",
  "source": "marketwatch",
  "type": "news",
  "title": "Is Nvidia a Republican or a Democrat? These political ETFs have voted.",
  "content": "ETFs that combine investing and politics tap into investors’ polarized views. Why they shouldn’t get your vote.",
  "url": "https://www.marketwatch.com/story/is-nvidia-a-republican-or-a-democrat-these-political-etfs-have-voted-ddb51f26?mod=mw_rss_topstories",
  "author": "MarketWatch",
  "published_at": "2025-08-18T15:22:00Z",
  "ingested_at": "2025-08-18T22:05:21.1114109+05:30",
  "metadata": {
    "guid": "WP-MKTW-0004391857"
  },
  "tags": [
    "marketwatch",
    "financial_news"
  ],
  "entities": null
}
